instrument_connector/__init__.py
instrument_connector/instrument_connector.py
instrument_connector-0.1.0.dist-info/LICENSE
instrument_connector-0.1.0.dist-info/METADATA
instrument_connector-0.1.0.dist-info/WHEEL
instrument_connector-0.1.0.dist-info/top_level.txt
instrument_connector-0.1.0.dist-info/RECORD
