Metadata-Version: 2.1
Name: instrument_connector
Version: 0.1.0
Summary: A Python library to connect to instruments via PyVISA
Author: Federico Guerra
Author-email: 
License: MIT
Classifier: Programming Language :: Python :: 3
Classifier: License :: OSI Approved :: MIT License
Classifier: Operating System :: OS Independent
Requires-Python: >=3.7
License-File: LICENSE
Requires-Dist: pyvisa
